lifeguard/__init__.py
lifeguard/auth.py
lifeguard/bootstrap.py
lifeguard/context.py
lifeguard/groups.py
lifeguard/http_client.py
lifeguard/logger.py
lifeguard/notifications.py
lifeguard/repositories.py
lifeguard/scheduler.py
lifeguard/server.py
lifeguard/settings.py
lifeguard/statuses.py
lifeguard/utils.py
lifeguard/validations.py
lifeguard/actions/__init__.py
lifeguard/actions/database.py
lifeguard/actions/email.py
lifeguard/actions/notifications.py
lifeguard/controllers/__init__.py
lifeguard/controllers/assets.py
lifeguard/controllers/groups.py
lifeguard-1.5.2.data/scripts/lifeguard
tests/__init__.py
tests/test_auth.py
tests/test_bootstrap.py
tests/test_controllers.py
tests/test_groups.py
tests/test_http_client.py
tests/test_lifeguard_core.py
tests/test_notifications.py
tests/test_repositories.py
tests/test_scheduler.py
tests/test_server.py
tests/test_settings.py
tests/test_validations.py
tests/actions/__init__.py
tests/actions/test_database.py
tests/actions/test_email.py
tests/actions/test_notification.py
tests/controllers/__init__.py
tests/controllers/test_assets.py
tests/controllers/test_groups.py
tests/fixtures/__init__.py
tests/fixtures/fixtures_repositories.py
tests/fixtures/mock_lifeguard_settings.py
lifeguard-1.5.2.dist-info/METADATA
lifeguard-1.5.2.dist-info/WHEEL
lifeguard-1.5.2.dist-info/top_level.txt
lifeguard-1.5.2.dist-info/RECORD
