Metadata-Version: 2.1
Name: lifeguard
Version: 1.5.2
Summary: Application to monitor your systems and give you the security to sleep peacefully at night
Home-page: https://github.com/LifeguardSystem/lifeguard
Author: Diego Rubin
Author-email: contact@diegorubin.dev
License: GPL2
Classifier: Development Status :: 5 - Production/Stable
Classifier: Intended Audience :: Developers
Classifier: Intended Audience :: Information Technology
Classifier: Programming Language :: Python
Classifier: Programming Language :: Python :: 3
Classifier: Topic :: System :: Monitoring
Requires-Dist: flask
Requires-Dist: flask-cors
Requires-Dist: schedule
Requires-Dist: gunicorn
Requires-Dist: requests
Requires-Dist: tabulate
Requires-Dist: PyYAML
